setuptools_cmake/CMakeLists.txt
setuptools_cmake/__init__.py
setuptools_cmake-1.1.dist-info/METADATA
setuptools_cmake-1.1.dist-info/WHEEL
setuptools_cmake-1.1.dist-info/top_level.txt
setuptools_cmake-1.1.dist-info/RECORD
