Metadata-Version: 2.1
Name: setuptools-cmake
Version: 1.1
Summary: A setuptools intrgration for CMake built extension modules
Author: TheClockTwister
Requires-Dist: pybind11[global]
Requires-Dist: click
Requires-Dist: colorama
